mkv_chapter_helper/__init__.py
mkv_chapter_helper/cli.py
mkv_chapter_helper/main.py
mkv_chapter_helper/processing.py
mkv_chapter_helper/utils.py
mkv_chapter_helper-1.0.1.dist-info/METADATA
mkv_chapter_helper-1.0.1.dist-info/WHEEL
mkv_chapter_helper-1.0.1.dist-info/entry_points.txt
mkv_chapter_helper-1.0.1.dist-info/licenses/LICENSE
mkv_chapter_helper-1.0.1.dist-info/RECORD
