Metadata-Version: 2.4
Name: mkv-chapter-helper
Version: 1.0.1
Summary: Embed chapters into an MKV file with the ability to mix timecodes and chapter names from multiple sources.
Author-email: nateify <nateify@users.noreply.github.com>
License-File: LICENSE
Keywords: automation,chaptergrabber,chapters,cli,matroska,media,mediainfo,metadata,mkv,ogm,remux,video,xml
Classifier: Development Status :: 5 - Production/Stable
Classifier: Intended Audience :: Developers
Classifier: Intended Audience :: End Users/Desktop
Classifier: License :: OSI Approved :: MIT License
Classifier: Operating System :: OS Independent
Classifier: Programming Language :: Python :: 3
Classifier: Programming Language :: Python :: 3.8
Classifier: Programming Language :: Python :: 3.9
Classifier: Programming Language :: Python :: 3.10
Classifier: Programming Language :: Python :: 3.11
Classifier: Programming Language :: Python :: 3.12
Classifier: Programming Language :: Python :: 3.13
Classifier: Topic :: Multimedia :: Video
Classifier: Topic :: Utilities
Requires-Python: >=3.8
